setup.cfg
setup.py
tex_table_and_img/__init__.py
tex_table_and_img/table_and_img_generate.py
tex_table_and_img.egg-info/PKG-INFO
tex_table_and_img.egg-info/SOURCES.txt
tex_table_and_img.egg-info/dependency_links.txt
tex_table_and_img.egg-info/not-zip-safe
tex_table_and_img.egg-info/top_level.txt