Metadata-Version: 2.2
Name: tex_table_and_img
Version: 0.0
Summary: Make table and img for tex
Author-email: brudloord@yandex.ru
Dynamic: author-email
Dynamic: summary
